tomek/__init__.py
tomek/_person.cpython-39-x86_64-linux-gnu.so
tomek/_person.py
tomek/usage.py
tomek_marstomek-0.0.6.dist-info/LICENSE
tomek_marstomek-0.0.6.dist-info/METADATA
tomek_marstomek-0.0.6.dist-info/WHEEL
tomek_marstomek-0.0.6.dist-info/top_level.txt
tomek_marstomek-0.0.6.dist-info/RECORD
