Metadata-Version: 2.1
Name: tomek-marstomek
Version: 0.0.6
Summary: My CFFI python example hash table
Home-page: http://mt-software.info/
Author: Tomasz Marszalek
Author-email: marstomek@gmail.com
License: UNKNOWN
Platform: linux
Classifier: Programming Language :: Python :: 3
Classifier: License :: OSI Approved :: MIT License
Classifier: Operating System :: POSIX :: Linux
Requires-Python: >=3.6
License-File: LICENSE
Requires-Dist: cffi
